chessam/__init__.py
chessam/src/Pieces.py
chessam/src/__init__.py
chessam/src/board_functions.py
chessam/src/bot_vs_bot.py
chessam/src/gui.py
chessam/src/human_vs_bot.py
chessam/src/human_vs_human.py
chessam/utilities/__init__.py
chessam/utilities/image_resizing.py
chessam/utilities/images_dict.py
chessam-0.1.dist-info/METADATA
chessam-0.1.dist-info/WHEEL
chessam-0.1.dist-info/top_level.txt
chessam-0.1.dist-info/RECORD
